purecpp_libs_t/RagPUREAI_libs.cpython-310-x86_64-linux-gnu.so
purecpp_libs_t/__init__.py
purecpp_libs_t.libs/libgomp-14f972ab.so.1.0.0
purecpp_libs_t-0.0.416.dist-info/METADATA
purecpp_libs_t-0.0.416.dist-info/WHEEL
purecpp_libs_t-0.0.416.dist-info/top_level.txt
purecpp_libs_t-0.0.416.dist-info/RECORD
